<?xml version="1.0" encoding="utf-8"?>
<abapGit version="v1.0.0" serializer="LCL_OBJECT_W3MI" serializer_version="v2.0.0">
 <asx:abap xmlns:asx="http://www.sap.com/abapxml" version="1.0">
  <asx:values>
   <NAME>/MBTOOLS/ACCESS_PASS_TN</NAME>
   <TEXT>MBT Access Pass (Thumbnail)</TEXT>
   <PARAMS>
    <WWWPARAMS>
     <RELID>MI</RELID>
     <OBJID>/MBTOOLS/ACCESS_PASS_TN</OBJID>
     <NAME>fileextension</NAME>
     <VALUE>.jpg</VALUE>
    </WWWPARAMS>
    <WWWPARAMS>
     <RELID>MI</RELID>
     <OBJID>/MBTOOLS/ACCESS_PASS_TN</OBJID>
     <NAME>filename</NAME>
     <VALUE>MBT_Access_Pass_TN.jpg</VALUE>
    </WWWPARAMS>
    <WWWPARAMS>
     <RELID>MI</RELID>
     <OBJID>/MBTOOLS/ACCESS_PASS_TN</OBJID>
     <NAME>mimetype</NAME>
     <VALUE>image/jpeg</VALUE>
    </WWWPARAMS>
   </PARAMS>
  </asx:values>
 </asx:abap>
</abapGit>
